{"shenxianshu_all":{"num":411,"unit_price":11769,"max_unit_price":39629,"min_unit_price":4800,"price":128,"maxPrice":2400,"minPrice":12,"size":89,"minSize":12,"maxSize":727,"rooms":0,"decoration":""},"shenxianshu_1":{"num":223,"unit_price":10875,"max_unit_price":39629,"min_unit_price":4800,"price":77,"maxPrice":2400,"minPrice":12,"size":49,"minSize":12,"maxSize":727,"rooms":1,"decoration":""},"shenxianshu_2":{"num":79,"unit_price":10756,"max_unit_price":19181,"min_unit_price":7368,"price":88,"maxPrice":215,"minPrice":51,"size":81,"minSize":50,"maxSize":147,"rooms":2,"decoration":""},"shenxianshu_3":{"num":84,"unit_price":11764,"max_unit_price":20127,"min_unit_price":7002,"price":143,"maxPrice":320,"minPrice":65,"size":116,"minSize":77,"maxSize":243,"rooms":3,"decoration":""},"shenxianshu_4":{"num":53,"unit_price":14597,"max_unit_price":24561,"min_unit_price":7083,"price":270,"maxPrice":700,"minPrice":68,"size":177,"minSize":75,"maxSize":344,"rooms":4,"decoration":""},"shenxianshu_1_de1":{"num":17,"unit_price":13007,"max_unit_price":31633,"min_unit_price":8934,"price":258,"maxPrice":2300,"minPrice":32,"size":119,"minSize":29,"maxSize":727,"rooms":1,"decoration":"de1"},"shenxianshu_2_de1":{"num":15,"unit_price":12240,"max_unit_price":19181,"min_unit_price":8088,"price":100,"maxPrice":200,"minPrice":52,"size":79,"minSize":51,"maxSize":147,"rooms":2,"decoration":"de1"},"shenxianshu_3_de1":{"num":10,"unit_price":14227,"max_unit_price":19583,"min_unit_price":7539,"price":183,"maxPrice":275,"minPrice":66,"size":123,"minSize":87,"maxSize":158,"rooms":3,"decoration":"de1"},"shenxianshu_4_de1":{"num":11,"unit_price":17586,"max_unit_price":24561,"min_unit_price":11071,"price":341,"maxPrice":700,"minPrice":155,"size":189,"minSize":140,"maxSize":285,"rooms":4,"decoration":"de1"},"summary":"均价:11769 在售套数:411 平均总价:128 平均面积:89,1居 均价:10875 在售套数:223 平均总价:77 平均面积:49,2居 均价:10756 在售套数:79 平均总价:88 平均面积:81,3居 均价:11764 在售套数:84 平均总价:143 平均面积:116,4居 均价:14597 在售套数:53 平均总价:270 平均面积:177,1居 精装修 均价:13007 在售套数:17 平均总价:258 平均面积:119,2居 精装修 均价:12240 在售套数:15 平均总价:100 平均面积:79,3居 精装修 均价:14227 在售套数:10 平均总价:183 平均面积:123,4居 精装修 均价:17586 在售套数:11 平均总价:341 平均面积:189,均价:13079 在售套数:570 平均总价:205 平均面积:154,1居 均价:10915 在售套数:154 平均总价:114 平均面积:92,2居 均价:13539 在售套数:110 平均总价:123 平均面积:91,3居 均价:14255 在售套数:203 平均总价:222 平均面积:162,4居 均价:13417 在售套数:120 平均总价:346 平均面积:263,1居 精装修 均价:11668 在售套数:30 平均总价:109 平均面积:96,2居 精装修 均价:13971 在售套数:26 平均总价:126 平均面积:89,3居 精装修 均价:17010 在售套数:32 平均总价:234 平均面积:144,4居 精装修 均价:14815 在售套数:15 平均总价:323 平均面积:221,均价:21086 在售套数:395 平均总价:364 平均面积:148,1居 均价:12286 在售套数:119 平均总价:77 平均面积:58,2居 均价:21321 在售套数:46 平均总价:201 平均面积:92,3居 均价:22124 在售套数:61 平均总价:336 平均面积:150,4居 均价:25723 在售套数:179 平均总价:599 平均面积:225,1居 精装修 均价:17092 在售套数:13 平均总价:104 平均面积:58,2居 精装修 均价:23720 在售套数:17 平均总价:221 平均面积:93,3居 精装修 均价:24237 在售套数:28 平均总价:357 平均面积:147,4居 精装修 均价:24727 在售套数:37 平均总价:526 平均面积:209","xinhuizhan_all":{"num":570,"unit_price":13079,"max_unit_price":52702,"min_unit_price":3461,"price":205,"maxPrice":3210,"minPrice":10,"size":154,"minSize":12,"maxSize":2005,"rooms":0,"decoration":""},"xinhuizhan_1":{"num":154,"unit_price":10915,"max_unit_price":52702,"min_unit_price":3461,"price":114,"maxPrice":3210,"minPrice":10,"size":92,"minSize":12,"maxSize":2005,"rooms":1,"decoration":""},"xinhuizhan_2":{"num":110,"unit_price":13539,"max_unit_price":25843,"min_unit_price":8333,"price":123,"maxPrice":230,"minPrice":53,"size":91,"minSize":51,"maxSize":137,"rooms":2,"decoration":""},"xinhuizhan_3":{"num":203,"unit_price":14255,"max_unit_price":28295,"min_unit_price":8072,"price":222,"maxPrice":550,"minPrice":96,"size":162,"minSize":88,"maxSize":378,"rooms":3,"decoration":""},"xinhuizhan_4":{"num":120,"unit_price":13417,"max_unit_price":25325,"min_unit_price":6250,"price":346,"maxPrice":1300,"minPrice":100,"size":263,"minSize":104,"maxSize":735,"rooms":4,"decoration":""},"xinhuizhan_1_de1":{"num":30,"unit_price":11668,"max_unit_price":15605,"min_unit_price":9837,"price":109,"maxPrice":360,"minPrice":35,"size":96,"minSize":35,"maxSize":323,"rooms":1,"decoration":"de1"},"xinhuizhan_2_de1":{"num":26,"unit_price":13971,"max_unit_price":23596,"min_unit_price":9966,"price":126,"maxPrice":210,"minPrice":82,"size":89,"minSize":75,"maxSize":118,"rooms":2,"decoration":"de1"},"xinhuizhan_3_de1":{"num":32,"unit_price":17010,"max_unit_price":26786,"min_unit_price":10757,"price":234,"maxPrice":360,"minPrice":130,"size":144,"minSize":88,"maxSize":297,"rooms":3,"decoration":"de1"},"xinhuizhan_4_de1":{"num":15,"unit_price":14815,"max_unit_price":20339,"min_unit_price":9539,"price":323,"maxPrice":720,"minPrice":180,"size":221,"minSize":135,"maxSize":380,"rooms":4,"decoration":"de1"},"jinrongcheng_all":{"num":395,"unit_price":21086,"max_unit_price":62130,"min_unit_price":4667,"price":364,"maxPrice":2500,"minPrice":14,"size":148,"minSize":10,"maxSize":482,"rooms":0,"decoration":""},"jinrongcheng_1":{"num":119,"unit_price":12286,"max_unit_price":62130,"min_unit_price":4000,"price":77,"maxPrice":630,"minPrice":14,"size":58,"minSize":13,"maxSize":364,"rooms":1,"decoration":""},"jinrongcheng_2":{"num":46,"unit_price":21321,"max_unit_price":30971,"min_unit_price":10137,"price":201,"maxPrice":452,"minPrice":75,"size":92,"minSize":65,"maxSize":176,"rooms":2,"decoration":""},"jinrongcheng_3":{"num":61,"unit_price":22124,"max_unit_price":40741,"min_unit_price":8357,"price":336,"maxPrice":730,"minPrice":120,"size":150,"minSize":93,"maxSize":257,"rooms":3,"decoration":""},"jinrongcheng_4":{"num":179,"unit_price":25723,"max_unit_price":66298,"min_unit_price":14159,"price":599,"maxPrice":2500,"minPrice":160,"size":225,"minSize":110,"maxSize":482,"rooms":4,"decoration":""},"jinrongcheng_1_de1":{"num":13,"unit_price":17092,"max_unit_price":36561,"min_unit_price":11719,"price":104,"maxPrice":310,"minPrice":61,"size":58,"minSize":46,"maxSize":84,"rooms":1,"decoration":"de1"},"jinrongcheng_2_de1":{"num":17,"unit_price":23720,"max_unit_price":30971,"min_unit_price":13223,"price":221,"maxPrice":310,"minPrice":90,"size":93,"minSize":65,"maxSize":121,"rooms":2,"decoration":"de1"},"jinrongcheng_3_de1":{"num":28,"unit_price":24237,"max_unit_price":40741,"min_unit_price":12903,"price":357,"maxPrice":550,"minPrice":120,"size":147,"minSize":93,"maxSize":239,"rooms":3,"decoration":"de1"},"jinrongcheng_4_de1":{"num":37,"unit_price":24727,"max_unit_price":34722,"min_unit_price":16974,"price":526,"maxPrice":1250,"minPrice":240,"size":209,"minSize":126,"maxSize":360,"rooms":4,"decoration":"de1"}}